MANIFEST.in
setup.py
suche/__init__.py
suche/suche_config.json
suche.egg-info/PKG-INFO
suche.egg-info/SOURCES.txt
suche.egg-info/dependency_links.txt
suche.egg-info/not-zip-safe
suche.egg-info/requires.txt
suche.egg-info/top_level.txt