Metadata-Version: 1.0
Name: suche
Version: 0.5.1
Summary: Elasticsearch Export Framework
Home-page: http://github.com/sachinvettithanam/suche
Author: sachin philip mathew
Author-email: me@imsach.in
License: MIT
Platform: UNKNOWN
